brestclient/__init__.py
brestclient/__main__.py
brestclient/command_line_ui.py
brestclient/http_stuff.py
brestclient/parsers.py
brestclient/pretty_print.py
brestclient/request_picker.py
brestclient/utils.py
brestclient/variables.py
brestclient-0.2.0.dist-info/METADATA
brestclient-0.2.0.dist-info/WHEEL
brestclient-0.2.0.dist-info/entry_points.txt
brestclient-0.2.0.dist-info/RECORD
