Metadata-Version: 2.1
Name: brestclient
Version: 0.2.0
Summary: best terminal rest client
Home-page: https://github.com/e9000000000/brestclient
License: MIT
Author: e
Author-email: skipper224483@gmail.com
Requires-Python: >=3.11
Classifier: License :: OSI Approved :: MIT License
Classifier: Programming Language :: Python :: 3
Classifier: Programming Language :: Python :: 3.11
Classifier: Programming Language :: Python :: 3.12
Requires-Dist: requests (>=2.31.0,<3.0.0)
Project-URL: Repository, https://github.com/e9000000000/brestclient
